egi_pynetstation/NetStation.py
egi_pynetstation/__init__.py
egi_pynetstation/eci.py
egi_pynetstation/exceptions.py
egi_pynetstation/socket_wrapper.py
egi_pynetstation/tests/test_command.py
egi_pynetstation/tests/test_get_ntp_byte.py
egi_pynetstation/tests/test_get_ntp_float.py
egi_pynetstation/tests/test_package_event.py
egi_pynetstation/tests/test_parse_response.py
egi_pynetstation/util.py
egi_pynetstation-1.0.0.dist-info/LICENSE
egi_pynetstation-1.0.0.dist-info/METADATA
egi_pynetstation-1.0.0.dist-info/WHEEL
egi_pynetstation-1.0.0.dist-info/RECORD
