Metadata-Version: 2.1
Name: egi_pynetstation
Version: 1.0.0
Summary: Magstim-EGI EEG amplifier NetStation API
Home-page: https://egi-pynetstation.readthedocs.io/en/latest/
License: MIT
Author: Joshua Teves
Author-email: joshua.teves@nih.gov
Requires-Python: >=3.8,<4.0
Classifier: License :: OSI Approved :: MIT License
Classifier: Programming Language :: Python :: 3
Classifier: Programming Language :: Python :: 3.8
Classifier: Programming Language :: Python :: 3.9
Classifier: Programming Language :: Python :: 3.10
Classifier: Programming Language :: Python :: 3.11
Requires-Dist: ntplib (>=0.4.0,<0.5.0)
Project-URL: Repository, https://github.com/nimh-sfim/egi-pynetstation
